{
  "name": "Valtech",
  "start": 2021,
  "end": 2022,
  "title": "Data Science Consultant",
  "optional_1": null,
  "optional_2": null,
  "description": {
    "short": "Worked on many data science projects utilising supervised and un-supervised machine learning methods. Some projects undertaken included time series forecasting of order and revenue numbers with Facebook Prophet, clustering survey and website visitor data for website personalisation.",
    "long": "Lorem ipsum dolor sit amet",
    "bartender": {
      "short": "I bartended sooooo much. I am super cool.Maybe you should hire me.... ;)",
      "long": "I bartended sooooo much. I am super cool.Maybe you should hire me.... ;) LOREM IPSUM DOLOR SIT AMET"
    }
  }
}
